amac/__init__.py
amac/mac_ggm.py
amac/proofs.py
amac/scheme.py
amac/utils.py
amac-0.0.1.dist-info/LICENSE.txt
amac-0.0.1.dist-info/METADATA
amac-0.0.1.dist-info/RECORD
amac-0.0.1.dist-info/WHEEL
amac-0.0.1.dist-info/top_level.txt
