Metadata-Version: 2.1
Name: amac
Version: 0.0.1
Summary: Algebraic MACs and keyed-verification anonymous credentials.
Home-page: https://pypi.org/project/amac-lib
Author: Alberto Sonnino
Author-email: alberto.sonnino@ucl.ac.uk
License: UNKNOWN
Project-URL: Source, https://github.com/asonnino/amac
Project-URL: Paper, http://www0.cs.ucl.ac.uk/staff/S.Meiklejohn/files/ccs14.pdf
Project-URL: Bug Reports, https://github.com/asonnino/amac
Keywords: cryptography credentials privacy
Platform: UNKNOWN
Classifier: Development Status :: 3 - Alpha
Classifier: Intended Audience :: Science/Research
Classifier: Topic :: Security :: Cryptography
Classifier: License :: OSI Approved :: GNU General Public License v3 or later (GPLv3+)
Classifier: Programming Language :: Python :: 2.7
Classifier: Programming Language :: Python :: 3.5
Requires-Dist: petlib
